EasyVisitors/__init__.py
EasyVisitors/admin.py
EasyVisitors/apps.py
EasyVisitors/middleware.py
EasyVisitors/models.py
EasyVisitors/tests.py
EasyVisitors/views.py
EasyVisitors/migrations/0001_initial.py
EasyVisitors/migrations/__init__.py
EasyVisitors-0.1.0.dist-info/LICENSE
EasyVisitors-0.1.0.dist-info/METADATA
EasyVisitors-0.1.0.dist-info/WHEEL
EasyVisitors-0.1.0.dist-info/top_level.txt
EasyVisitors-0.1.0.dist-info/RECORD
