Metadata-Version: 2.1
Name: EasyVisitors
Version: 0.1.0
Summary: A simple counter to keep a record of number of visitors who visit your website.
Home-page: https://github.com/deekshant-w/EasyVisitor
Author: Deekshant Wadhwa
Author-email: deekshantwadhwa2000@gmail.com
License: UNKNOWN
Platform: UNKNOWN
Classifier: Programming Language :: Python :: 3
Classifier: License :: OSI Approved :: MIT License
Classifier: Operating System :: OS Independent
Requires-Python: >=3.6
